d_latch/d_latch.v
module d_latch(D, enable, reset, Q);
  
  input D, enable, reset;
  
  output reg Q;
  
  always @(D or enable or reset)
  
  if (!reset)  // reset is active low
      Q <= 0;
  
  else
    
    if (enable)
    
    Q <= D;
  
    
  
endmodule

d_latch/testbench.sv

// Testcase for D-Latch in Verilog

`include "d_latch.v"

module latch_tb;
 
  reg D; reg enable; reg reset;

  wire Q;
  
  integer i;
  
  d_latch test_latch(
    .D(D),
    .enable(enable),
    .reset(reset),
    .Q(Q)
  );
  
  initial
    begin
      
      $dumpfile("dump.vcd");
      $dumpvars(0, test_latch);
      
      $monitor("[%0t] D = %d en = %d reset = %d Q = %d", $time, D, enable, reset, Q);
      
      D = 1;
      enable = 0;
      reset = 0;
      
      #10 reset = 1;
      
      for (i=0; i!=10; i=i+1)
        begin
          #5 enable <= ~enable;
          
          #5 D <= i; 
          
        end
     
    end 
      
endmodule // half_adder_tb

d_latch/dump.vcd
$date
	Sun Jan 30 06:58:11 2022
$end
$version
	Icarus Verilog
$end
$timescale
	1s
$end
$scope module latch_tb $end
$scope module test_latch $end
$var wire 1 ! D $end
$var wire 1 " enable $end
$var wire 1 # reset $end
$var reg 1 $ Q $end
$upscope $end
$upscope $end
$enddefinitions $end
#0
$dumpvars
0$
0#
0"
1!
$end
#10
1#
#15
1$
1"
#20
0$
0!
#25
0"
#30
1!
#35
1$
1"
#40
0$
0!
#45
0"
#50
1!
#55
1$
1"
#60
0$
0!
#65
0"
#70
1!
#75
1$
1"
#80
0$
0!
#85
0"
#90
1!
#95
1$
1"
#100
0$
0!
#105
0"
#110
1!
