half_substrctor/half_substractor.v
// Implementation of half substrctor using structural modeling in  verilog

module half_sub(a, b, sub, borrow);
  input a;
  input b;
  output sub;
  output borrow;
  
  assign sub = a ^ b;
  assign borrow = ~a & b;
  
endmodule

half_substrctor/testbench.v
// testbench for half substractor

`timescale 1ns / 1ns

`include "half_substractor.v"

module half_sub_tb;
  
  reg  a;
  reg b;
  
  wire sub;
  wire borrow;

  half_sub half_sub_inst(
    
    .a(a),
    .b(b),
    .sub(sub),
    .borrow(borrow)
  );
  
  initial 
    begin
      
      $dumpfile("gates_wave.vcd");
      $dumpvars(1, a, b, sub, borrow);
		
      a = 1;
      b = 0;
      
      #100 $finish;
      
    end
  
  always #10 a=~a;

  always #5 b=~b;

  always @(a or b)

    $monitor("At TIME(in ns)=%t, a=%d b=%d Difference = %d Borrow = %d", $time, a, b, sub, borrow);  

endmodule

half_substrctor/gates_wave.vcd
$date
      Sat Jan 29 06:00:40 2022

$end
$version
      Veriwell 2.8.7
$end
$timescale
      1ns
$end


$scope module half_sub_tb $end
$var reg       1 !    a  $end
$var reg       1 "    b  $end
$var wire      1 #    sub  $end
$var wire      1 $    borrow  $end
$upscope $end

$enddefinitions      $end
#0
$dumpvars
0$
1#
0"
1!
$end
#5
1"
0#
#10
0!
0"
#15
1"
1$
1#
#20
1!
0"
0$
#25
1"
0#
#30
0!
0"
#35
1"
1$
1#
#40
1!
0"
0$
#45
1"
0#
#50
0!
0"
#55
1"
1$
1#
#60
1!
0"
0$
#65
1"
0#
#70
0!
0"
#75
1"
1$
1#
#80
1!
0"
0$
#85
1"
0#
#90
0!
0"
#95
1"
1$
1#
