JK_flip_flop/jk_flip_flop.v
// JK flip flop in verilog using behavioural modeling

module JK_flip_flop(J, K, clk , Q);
  
  input J, K, clk;
  
  output reg Q;
  
  always @(posedge clk)
  
    if(J==1 & K==0) 
      Q <= 1;
  
  	else if(J==0 & K==1)
      Q <= 0;
    
  else if(J==0 & K==0)
      Q <= Q;
  	
  	else
      Q <= ~Q;
     
endmodule

JK_flip_flop/testbench.v

// Testcase for JK Flip Flop in Verilog

`include "jk_flip_flop.v"

module flip_flop_tb;
 
  reg J; reg K; reg clk;

  wire Q;
  
  integer i;
  
  JK_flip_flop test_flip_flop(
    .J(J),
    .K(K),
    .clk(clk),
    .Q(Q)
  );
  
  
  // clock signal
  initial 
    begin
  		clk=0;
     	forever #10 clk = ~clk;  
	end
  
  initial
    
    begin
      
      $dumpfile("dump.vcd");
      $dumpvars(0, test_flip_flop);
      
      $monitor("[%0t] clk = %d J = %d R = %d K = %d", $time, clk, J, K, Q);
     
    end
  
  initial 
    begin 
 		J= 1; K= 0;
 		#45 J= 0; K= 1; 
 		#69 J= 0; K= 0; 
 		#42  J= 1; K=1;
    	#7 J= 0; K= 1; 
 		#21 J= 0; K= 0; 
 		#18  J= 1; K=1;
    	#65 J= 0; K= 1; 
 		#11 J= 0; K= 0; 
 		#34  J= 1; K=1;
    end
  
  initial
    #500 $finish;
      
endmodule // half_adder_tb

JK_flip_flop/dump.vcd
$date
	Sun Feb  6 06:26:50 2022
$end
$version
	Icarus Verilog
$end
$timescale
	1s
$end
$scope module flip_flop_tb $end
$scope module test_flip_flop $end
$var wire 1 ! J $end
$var wire 1 " K $end
$var wire 1 # clk $end
$var reg 1 $ Q $end
$upscope $end
$upscope $end
$enddefinitions $end
#0
$dumpvars
x$
0#
0"
1!
$end
#10
1$
1#
#20
0#
#30
1#
#40
0#
#45
1"
0!
#50
0$
1#
#60
0#
#70
1#
#80
0#
#90
1#
#100
0#
#110
1#
#114
0"
#120
0#
#130
1#
#140
0#
#150
1#
#156
1"
1!
#160
0#
#163
0!
#170
1#
#180
0#
#184
0"
#190
1#
#200
0#
#202
1"
1!
#210
1$
1#
#220
0#
#230
0$
1#
#240
0#
#250
1$
1#
#260
0#
#267
0!
#270
0$
1#
#278
0"
#280
0#
#290
1#
#300
0#
#310
1#
#312
1"
1!
#320
0#
#330
1$
1#
#340
0#
#350
0$
1#
#360
0#
#370
1$
1#
#380
0#
#390
0$
1#
#400
0#
#410
1$
1#
#420
0#
#430
0$
1#
#440
0#
#450
1$
1#
#460
0#
#470
0$
1#
#480
0#
#490
1$
1#
