full_substractor/full_substractor.v
// Implementation of full substrctor using dataflow modeling

  
module full_sub(x, y, Bin, sub, Bout);
  input x;
  input y;
  input Bin; // borrow in
  output sub;
  output Bout;  // borrow out
  
  wire i, j, k; // for interconnections
  
  // substraction
  assign sub = x ^ y ^ Bin;
  
  // borrow
  assign i = ~x & y;
  assign j = y & Bin;
  assign k = ~x & Bin;
  
  assign Bout = i | j | k;
  
endmodule

full_substractor/testbench.v
// testbench for half substractor

`timescale 1ns / 1ns

`include "full_substractor.v"

module full_sub_tb;
  
  reg  x, y, Bin;
  
  wire sub, Bout;

  full_sub full_sub_inst(
    
    .x(x),
    .y(y),
    .Bin(Bin),
    .sub(sub),
    .Bout(Bout)
  );
  
  initial 
    begin
      
      $dumpfile("gates_wave.vcd");
      $dumpvars(1, x, y, Bin, sub, Bout);
		
      x = 1;
      y = 0;
      Bin = 1;
      
      #100 $finish;
      
    end
  
  always #5 x = ~x;

  always #10 y = ~y;
  
  always #5  Bin = ~Bin;

  always @(x or y or Bin)

    $monitor("At TIME(in ns)=%t, a=%d b=%d Bin=%d Difference = %d Borrow = %d", $time, x, y, Bin, sub, Bout);  

endmodule

full_substractor/gates_wave.vcd
$date
      Sat Jan 29 06:52:30 2022

$end
$version
      Veriwell 2.8.7
$end
$timescale
      1ns
$end


$scope module full_sub_tb $end
$var reg       1 !    x  $end
$var reg       1 "    y  $end
$var reg       1 #    Bin  $end
$var wire      1 $    sub  $end
$var wire      1 %    Bout  $end
$upscope $end

$enddefinitions      $end
#0
$dumpvars
0%
0$
1#
0"
1!
$end
#5
0!
0#
#10
1"
1!
1#
1$
1%
#15
0!
0#
#20
0"
1!
1#
0$
0%
#25
0!
0#
#30
1"
1!
1#
1$
1%
#35
0!
0#
#40
0"
1!
1#
0$
0%
#45
0!
0#
#50
1"
1!
1#
1$
1%
#55
0!
0#
#60
0"
1!
1#
0$
0%
#65
0!
0#
#70
1"
1!
1#
1$
1%
#75
0!
0#
#80
0"
1!
1#
0$
0%
#85
0!
0#
#90
1"
1!
1#
1$
1%
#95
0!
0#
