SR_flip_flop/sr_flip_flop.v
// SR Flip FLop in Verilog using Behavioural Modeling
module sr_flip_flop(S, R, clk , Q);
  
  input S, R, clk;
  
  output reg Q;
  
  always @(posedge clk)
  
    if(S==1)
      Q <= 1;
  
  	else if(R==1)
      Q <= 0;
    
  	else if(S==0 & R==0)
      Q <= Q;
     
endmodule

SR_flip_flop/testbench.v

// Testcase for SR Flip Flop in Verilog

`include "sr_flip_flop.v"

module flip_flop_tb;
 
  reg S; reg R; reg clk;

  wire Q;
  
  integer i;
  
  sr_flip_flop test_flip_flop(
    .S(S),
    .R(R),
    .clk(clk),
    .Q(Q)
  );
  
  
  // clock signal
  initial 
    begin
  		clk=0;
     	forever #10 clk = ~clk;  
	end
  
  initial
    
    begin
      
      $dumpfile("dump.vcd");
      $dumpvars(0, test_flip_flop);
      
      $monitor("[%0t] clk = %d S = %d R = %d Q = %d", $time, clk, S, R, Q);
     
    end
  
  initial 
    begin 
 		S= 1; R= 0;
 		#50 S= 0; R= 1; 
 		#50 S= 0; R= 0; 
 		#50  S= 1; R=1;
    	#50 S= 0; R= 1; 
 		#50 S= 0; R= 0; 
 		#50  S= 1; R=1;
    	#50 S= 0; R= 1; 
 		#50 S= 0; R= 0; 
 		#50  S= 1; R=1;
    end
  
  initial
    #500 $finish;
      
endmodule

SR_flip_flop/dump.vcd
$date
	Sun Feb  6 05:52:36 2022
$end
$version
	Icarus Verilog
$end
$timescale
	1s
$end
$scope module flip_flop_tb $end
$scope module test_flip_flop $end
$var wire 1 ! R $end
$var wire 1 " S $end
$var wire 1 # clk $end
$var reg 1 $ Q $end
$upscope $end
$upscope $end
$enddefinitions $end
#0
$dumpvars
x$
0#
1"
0!
$end
#10
1$
1#
#20
0#
#30
1#
#40
0#
#50
0$
1#
1!
0"
#60
0#
#70
1#
#80
0#
#90
1#
#100
0#
0!
#110
1#
#120
0#
#130
1#
#140
0#
#150
1$
1#
1!
1"
#160
0#
#170
1#
#180
0#
#190
1#
#200
0#
0"
#210
0$
1#
#220
0#
#230
1#
#240
0#
#250
1#
0!
#260
0#
#270
1#
#280
0#
#290
1#
#300
0#
1!
1"
#310
1$
1#
#320
0#
#330
1#
#340
0#
#350
0$
1#
0"
#360
0#
#370
1#
#380
0#
#390
1#
#400
0#
0!
#410
1#
#420
0#
#430
1#
#440
0#
#450
1$
1#
1!
1"
